{
  "title": "Electrical Solutions Bristol | Domestic electrician in Bristol BS16",
  "description": "High-end domestic electrics across Bristol and the BS postcodes. Lawrence fits lighting and downlights, upgrades consumer units, rewires and chases down faults, sorting the safety first and leaving the job tidy. Rated 5.0 on Google from 135 reviews.",
  "ogImage": "/og.png",
  "metadataBase": "https://electrical-solutions-bristol-ltd.vercel.app",
  "buildId": "electrical-solutions-bristol-ltd:20260613-1",
  "webfortradesSlug": "electrical-solutions-bristol-ltd"
}
